regulome_app/__init__.py
regulome_app/config.py
regulome_app/regulome.cfg.template
regulome_app/run.py
regulome_app/regulome_plot/plot_IRB_00LoadAndCreateObjects.R
regulome_app/regulome_plot/plot_IRB_01Legend.R
regulome_app/regulome_plot/plot_IRB_02IdeogramHeader.R
regulome_app/regulome_plot/plot_IRB_03SNPmotifOpenChrom.R
regulome_app/regulome_plot/plot_IRB_04PlotRegions.R
regulome_app/regulome_plot/plot_IRB_05PlotTFBS.R
regulome_app/regulome_plot/plot_IRB_06PlotGenes.R
regulome_app/regulome_plot/plot_IRB_config.R
regulome_app/regulome_plot/plot_IRB_main.R
regulome_app/regulome_plot/plot_IRB_testVariables.R
regulome_app/webapp/__init__.py
regulome_app/webapp/app.py
regulome_app/webapp/models.py
regulome_app/webapp/views.py
regulome_app/webapp/static/css/ie10-viewport-bug-workaround.css
regulome_app/webapp/static/css/regulome.css
regulome_app/webapp/static/css/style.css
regulome_app/webapp/static/css/theme.css
regulome_app/webapp/static/data/hg18_UCSC_RefSeq_genes_simple.txt
regulome_app/webapp/static/data/hg19_UCSC_RefSeq_genes_simple.txt
regulome_app/webapp/static/data/hg38_UCSC_RefSeq_genes_simple.txt
regulome_app/webapp/static/images/ajax-loader.gif
regulome_app/webapp/static/images/favicon.ico
regulome_app/webapp/static/images/favicon32b.ico
regulome_app/webapp/static/images/regulome_logo.png
regulome_app/webapp/static/images/regulome_logo_hover.png
regulome_app/webapp/static/images/spin.gif
regulome_app/webapp/static/python/__init__.py
regulome_app/webapp/static/python/data.py
regulome_app/webapp/static/python/info.py
regulome_app/webapp/static/python/intro.py
regulome_app/webapp/static/python/plot.py
regulome_app/webapp/static/python/utils.py
regulome_app/webapp/templates/base.html
regulome_app/webapp/templates/contact.html
regulome_app/webapp/templates/credits.html
regulome_app/webapp/templates/data.html
regulome_app/webapp/templates/info.html
regulome_app/webapp/templates/intro.html
regulome_web-2.0.0.dist-info/DESCRIPTION.rst
regulome_web-2.0.0.dist-info/METADATA
regulome_web-2.0.0.dist-info/RECORD
regulome_web-2.0.0.dist-info/WHEEL
regulome_web-2.0.0.dist-info/entry_points.txt
regulome_web-2.0.0.dist-info/metadata.json
regulome_web-2.0.0.dist-info/top_level.txt
