Metadata-Version: 2.0
Name: regulome-web
Version: 2.0.0
Summary: Human Islet Regulome Browser
Home-page: https://bitbucket.org/batterio/regulome_web
Author: Loris Mularoni
Author-email: loris@mularoni.com
License: MIT License
Download-URL: https://bitbucket.org/batterio/regulome_web/get/2.0.0.tar.gz
Platform: UNKNOWN
Classifier: Development Status :: 5 - Production/Stable
Classifier: Intended Audience :: Developers
Classifier: License :: OSI Approved :: MIT License
Classifier: Environment :: Console
Classifier: Intended Audience :: Science/Research
Classifier: Natural Language :: English
Classifier: Operating System :: OS Independent
Classifier: Programming Language :: Python
Classifier: Programming Language :: Python :: 3.5
Classifier: Programming Language :: Python :: 3.6
Classifier: Topic :: Scientific/Engineering
Classifier: Topic :: Scientific/Engineering :: Bio-Informatics
Requires-Dist: Brython
Requires-Dist: Click
Requires-Dist: Flask
Requires-Dist: Jinja2
